abdcon/__init__.py
abdcon-0.0.1.dist-info/LICENSE.txt
abdcon-0.0.1.dist-info/METADATA
abdcon-0.0.1.dist-info/WHEEL
abdcon-0.0.1.dist-info/top_level.txt
abdcon-0.0.1.dist-info/RECORD
