Metadata-Version: 2.1
Name: abdcon
Version: 0.0.1
Summary: computing functions for electrical engineers
Home-page: https://github.com/iam-abdul
Author: iron man
Author-email: mohammadabdulrehman739@gmail.com
License: UNKNOWN
Platform: UNKNOWN
Classifier: Programming Language :: Python :: 3
Classifier: License :: OSI Approved :: MIT License
Classifier: Operating System :: OS Independent
Requires-Dist: numpy
